qzx.py
Commands/__init__.py
Commands/DevCommands/AnalyzeComplexity.py
Commands/DevCommands/CompareFiles.py
Commands/DevCommands/CreateDocTemplatePython.py
Commands/DevCommands/__init__.py
Commands/DevelopmentCommands/MakeScaffProgramC.py
Commands/DevelopmentCommands/MakeScaffProgramCpp.py
Commands/DevelopmentCommands/MakeScaffProgramPython.py
Commands/DevelopmentCommands/MakeScaffProgramRust.py
Commands/FileCommands/ChangePermissions.py
Commands/FileCommands/CopyFile.py
Commands/FileCommands/CountLinesInFile.py
Commands/FileCommands/CreateDirectory.py
Commands/FileCommands/DeleteFile.py
Commands/FileCommands/DownloadFile.py
Commands/FileCommands/FindFiles.py
Commands/FileCommands/FindLargeFiles.py
Commands/FileCommands/FindText.py
Commands/FileCommands/GetHumanLanguageStatsFromFile.py
Commands/FileCommands/GetProgrammingLanguageStatsFromFile.py
Commands/FileCommands/ListFiles.py
Commands/FileCommands/MoveFile.py
Commands/FileCommands/ReadFile.py
Commands/FileCommands/TouchFile.py
Commands/FileCommands/WonderFileTypeMagic.py
Commands/FileCommands/WonderIfDirectoryEmpty.py
Commands/FileCommands/WonderIfFileEmpty.py
Commands/FileCommands/WonderIfFileIsBinary.py
Commands/FileCommands/__init__.py
Commands/SystemCommands/ClearScreen.py
Commands/SystemCommands/CommandsBridge.py
Commands/SystemCommands/CurrentDir.py
Commands/SystemCommands/GetCPULoad.py
Commands/SystemCommands/GetCurrentDate.py
Commands/SystemCommands/GetCurrentTime.py
Commands/SystemCommands/GetCurrentUser.py
Commands/SystemCommands/GetDiskInfo.py
Commands/SystemCommands/GetDiskName.py
Commands/SystemCommands/GetGPULoad.py
Commands/SystemCommands/GetRAMInfo.py
Commands/SystemCommands/GetSmartValues.py
Commands/SystemCommands/KillProcess.py
Commands/SystemCommands/ListProcesses.py
Commands/SystemCommands/QZXVersion.py
Commands/SystemCommands/RunScript.py
Commands/SystemCommands/Shell.py
Commands/SystemCommands/SystemInfo.py
Commands/SystemCommands/Term.py
Commands/SystemCommands/Terminal.py
qzx-0.2.2.dist-info/METADATA
qzx-0.2.2.dist-info/WHEEL
qzx-0.2.2.dist-info/entry_points.txt
qzx-0.2.2.dist-info/top_level.txt
qzx-0.2.2.dist-info/RECORD
