Metadata-Version: 2.2
Name: qzx
Version: 0.2.2
Summary: QZX - Quick Zap Exchange - Command line tool for automating common tasks across platforms
Home-page: https://github.com/alesanGreat/QZX-Quick-Zap-Exchange
Author: Alejandro Sánchez
Author-email: alesangreat@gmail.com
Classifier: Programming Language :: Python :: 3
Classifier: License :: OSI Approved :: MIT License
Classifier: Operating System :: OS Independent
Requires-Python: >=3.6
Requires-Dist: psutil
Requires-Dist: pyreadline3
Provides-Extra: win
Requires-Dist: python-magic-bin; extra == "win"
Provides-Extra: unix
Requires-Dist: python-magic; extra == "unix"
Dynamic: author
Dynamic: author-email
Dynamic: classifier
Dynamic: description
Dynamic: description-content-type
Dynamic: home-page
Dynamic: provides-extra
Dynamic: requires-dist
Dynamic: requires-python
Dynamic: summary
